Workbook
Name Participante: 'Aporte Participantes Programa'!#REF!

Sheet Presupuesto Total
B1: PROGRAMA TECNOLÓGICO BITÁCORA: LÍNEA DE VIDA DE UN ACTIVO INMOBILIARIO
B3: PROGRAMAS TECNOLÓGICOS - PRESUPUESTO TOTAL
D4: SUBSIDIO TOTAL CORFO ($) | I4: APORTES PARTICIPANTES DEL PROGRAMA | R4: COSTO TOTAL PROGRAMA ($) | S4: MES INICIO | T4: MES TÉRMINO
B5: N° PROYECTO | C5: NOMBRE CORTO DEL PROYECTO | D5: RECURSOS HUMANOS ($) | E5: OPERACIÓN ($) | F5: INVERSIÓN ($) | G5: ADMINISTRACIÓN ($) | H5: SUBSIDIO TOTAL | I5: RECURSOS HUMANOS ($) | K5: OPERACIÓN ($) | M5: INVERSIÓN ($) | O5: ADMINISTRACIÓN ($) | Q5: APORTE TOTAL ($)
I6: APORTE PECUNIARIO ($) | J6: VALORIZADO | K6: APORTE PECUNIARIO ($) | L6: VALORIZADO | M6: APORTE PECUNIARIO ($) | N6: VALORIZADO | O6: APORTE PECUNIARIO ($) | P6: VALORIZADO
B7: P0 | C7: Gestión y administración del Programa (OBLIGATORIO) | D7: 550000000 | E7: 200000000 | F7: 15000000 | G7: 132000000 | H7: =SUM(D7:G7) -> 897000000 | I7: ='Aporte Participantes Programa'!E7 -> 600000000 | J7: ='Aporte Participantes Programa'!F7 -> 100000000 | K7: ='Aporte Participantes Programa'!G7 -> 200000000 | L7: ='Aporte Participantes Programa'!H7 -> 50000000 | M7: ='Aporte Participantes Programa'!I7 -> 40000000 | O7: ='Aporte Participantes Programa'!K7 -> 5000000 | Q7: =SUM(I7:P7) -> 995000000 | R7: =+H7+Q7 -> 1892000000 | S7: 1 | T7: 60
B8: P1 | C8: Evaluación del activo y búsqueda de terreno con IA (piloto DS49) | D8: 400000000 | E8: 75000000 | F8: 15000000 | G8: 40000000 | H8: =SUM(D8:G8) -> 530000000 | I8: ='Aporte Participantes Programa'!E9 -> 40000000 | J8: ='Aporte Participantes Programa'!F8+'Aporte Participantes Programa'!F9+'Aporte Participantes Programa'!F14 -> 226000000 | K8: ='Aporte Participantes Programa'!G9 -> 10000000 | L8: ='Aporte Participantes Programa'!H9+'Aporte Participantes Programa'!H8 -> 100000000 | M8: ='Aporte Participantes Programa'!I9 | N8: ='Aporte Participantes Programa'!J9 | O8: ='Aporte Participantes Programa'!K9 | P8: ='Aporte Participantes Programa'!L9 | Q8: =SUM(I8:P8) -> 376000000 | R8: =+H8+Q8 -> 906000000 | S8: 4 | T8: 53
B9: P2 | C9: Desarrollo y optimización del proyecto (CAPEX, OPEX y plazos) | D9: 400000000 | E9: 75000000 | F9: 15000000 | G9: 40000000 | H9: =SUM(D9:G9) -> 530000000 | I9: ='Aporte Participantes Programa'!E10 -> 40000000 | J9: ='Aporte Participantes Programa'!F9+'Aporte Participantes Programa'!F13 -> 129000000 | K9: ='Aporte Participantes Programa'!G10 -> 10000000 | L9: ='Aporte Participantes Programa'!H10 -> 50000000 | M9: ='Aporte Participantes Programa'!I10 | N9: ='Aporte Participantes Programa'!J10 | O9: ='Aporte Participantes Programa'!K10 | P9: ='Aporte Participantes Programa'!L10 | Q9: =SUM(I9:P9) -> 229000000 | R9: =+H9+Q9 -> 759000000 | S9: 4 | T9: 53
B10: P3 | C10: Integración de especialistas en obra ("Zapatilla") | D10: 400000000 | E10: 75000000 | F10: 15000000 | G10: 38000000 | H10: =SUM(D10:G10) -> 528000000 | I10: ='Aporte Participantes Programa'!E11 -> 40000000 | J10: ='Aporte Participantes Programa'!F11 -> 100000000 | K10: ='Aporte Participantes Programa'!G11 -> 10000000 | L10: ='Aporte Participantes Programa'!H11 -> 50000000 | M10: ='Aporte Participantes Programa'!I11 | N10: ='Aporte Participantes Programa'!J11 | O10: ='Aporte Participantes Programa'!K11 | P10: ='Aporte Participantes Programa'!L11 | Q10: =SUM(I10:P10) -> 200000000 | R10: =+H10+Q10 -> 728000000 | S10: 4 | T10: 53
B11: P4 | C11: Mantenimiento predictivo y línea de vida del activo | D11: 375000000 | E11: 75000000 | F11: 15000000 | G11: 50000000 | H11: =SUM(D11:G11) -> 515000000 | I11: ='Aporte Participantes Programa'!E12 -> 40000000 | J11: ='Aporte Participantes Programa'!F12 -> 100000000 | K11: ='Aporte Participantes Programa'!G12 -> 10000000 | L11: ='Aporte Participantes Programa'!H12 -> 50000000 | M11: ='Aporte Participantes Programa'!I12 | N11: ='Aporte Participantes Programa'!J12 | O11: ='Aporte Participantes Programa'!K12 | P11: ='Aporte Participantes Programa'!L12 | Q11: =SUM(I11:P11) -> 200000000 | R11: =+H11+Q11 -> 715000000 | S11: 4 | T11: 53
H12: =SUM(D12:G12) -> 0 | Q12: =SUM(I12:P12) -> 0 | R12: =+H12+Q12 -> 0
H13: =SUM(D13:G13) -> 0 | Q13: =SUM(I13:P13) -> 0 | R13: =+H13+Q13 -> 0
H14: =SUM(D14:G14) -> 0 | Q14: =SUM(I14:P14) -> 0 | R14: =+H14+Q14 -> 0
H15: =SUM(D15:G15) -> 0 | Q15: =SUM(I15:P15) -> 0 | R15: =+H15+Q15 -> 0
H16: =SUM(D16:G16) -> 0 | Q16: =SUM(I16:P16) -> 0 | R16: =+H16+Q16 -> 0
H17: =SUM(D17:G17) -> 0 | Q17: =+M17+N17 -> 0 | R17: =+H17+Q17 -> 0
C18: TOTAL PROGRAMA | D18: =SUM(D7:D17) -> 2125000000 | E18: =SUM(E7:E17) -> 500000000 | F18: =SUM(F7:F17) -> 75000000 | G18: =SUM(G7:G17) -> 300000000 | H18: =SUM(H7:H17) -> 3000000000 | I18: =SUM(I7:I17) -> 760000000 | J18: =SUM(J7:J17) -> 655000000 | K18: =SUM(K7:K17) -> 240000000 | ... R18: =SUM(R7:R17) -> 5000000000

Sheet Aporte Participantes Programa
B1: PROGRAMA TECNOLÓGICO BITÁCORA: LÍNEA DE VIDA DE UN ACTIVO INMOBILIARIO
B3: PROGRAMAS TECNOLÓGICOS - APORTE DE PARTICIPANTES
E4: DETALLE DEL APORTE AL PROGRAMA ($)
E5: RECURSOS HUMANOS ($) | G5: GASTOS OPERACIÓN ($) | I5: GASTOS INVERSIÓN ($) | K5: GASTOS ADMINISTRACIÓN ($) | M5: TOTAL
B6: ROL PARTICIPACIÓN PROGRAMA (Beneficiario, Coejecutor, Asociado, Interesdo) | C6: NOMBRE ENTIDAD | D6: PROYECTO(S) EN EL CUAL APORTA LA ENTIDAD | E6: PECUNIARIO | F6: VALORIZADO | G6: PECUNIARIO | H6: VALORIZADO | I6: PECUNIARIO | J6: VALORIZADO | K6: PECUNIARIO | L6: VALORIZADO
B7: Beneficiario | C7: DTE Consulting & Development SpA | D7: P0, P1, P2, P3, P4 | E7: 600000000 | F7: 100000000 | G7: 200000000 | H7: 50000000 | I7: 40000000 | K7: 5000000 | M7: =SUM(E7:K7) -> 995000000
B8: Coejecutor 1 | C8: Impulso Estratégico CX SpA | D8: P1 | F8: 99000000 | H8: 50000000 | M8: =SUM(E8:K8) -> 149000000
B9: Coejecutor 2 | C9: In-Data · | D9: P1 | E9: 40000000 | F9: 100000000 | G9: 10000000 | H9: 50000000 | M9: =SUM(E9:K9) -> 200000000
B10: Coejecutor 3 | C10: Geister · | D10: P2 | E10: 40000000 | F10: 100000000 | G10: 10000000 | H10: 50000000 | M10: =SUM(E10:K10) -> 200000000
B11: Coejecutor 4 | C11: ONDAC · | D11: P3 | E11: 40000000 | F11: 100000000 | G11: 10000000 | H11: 50000000 | M11: =SUM(E11:K11) -> 200000000
B12: Coejecutor 5 | C12: Calidad Cloud · | D12: P4 | E12: 40000000 | F12: 100000000 | G12: 10000000 | H12: 50000000 | M12: =SUM(E12:K12) -> 200000000
B13: Asociado 1 | C13: ANRI A.G. (Asociación Nacional de Revisores Independientes de Arquitectura) | D13: P2 | F13: 29000000 | M13: =SUM(E13:K13) -> 29000000
B14: Asociado 2 | C14: Molina Matta & Asociados | D14: P1 | F14: 27000000 | M14: =SUM(E14:K14) -> 27000000
M15: =SUM(E15:K15) -> 0
E16: =SUM(E7:E15) -> 760000000 | F16: =SUM(F7:F15) -> 655000000 | G16: =SUM(G7:G15) -> 240000000 | H16: =SUM(H7:H15) -> 300000000 | I16: =SUM(I7:I12) -> 40000000 | J16: =SUM(J7:J12) -> 0 | K16: =SUM(K7:K12) -> 5000000 | L16: =SUM(L7:L12) -> 0 | M16: =SUM(M7:M15) -> 2000000000
F20: =F8+F14/2 -> 112500000 | G20: =F20/3 -> 37500000
F21: =F9+F14/2 -> 113500000 | G21: =F21/2 -> 56750000
F22: =SUM(F20:F21) -> 226000000

Sheet Detalle Personal Preexistente
B1: PROGRAMA TECNOLÓGICO BITÁCORA: LÍNEA DE VIDA DE UN ACTIVO INMOBILIARIO
B3: PROGRAMAS TECNOLÓGICOS - DETALLES PERSONAL PREEXISTENTE
B4: N° | C4: NOMBRE | D4: FUNCIÓN | E4: NOMBRE ENTIDAD A LA QUE PERTENECE | F4: SUBSIDIO CORFO $ | G4: APORTE PROGRAMA TECNOLÓGICO | I4: =I4 -> #REF!
G5: Pecuniario $ | H5: Valorizado $
B6: 1 | C6: Carmen Gloria Zúñiga de Kartzow | D6: Directora del Programa | E6: DTE Consulting & Development SpA | I6: =F6+G6+H6 -> 0
B7: 2 | C7: Andrés Salgado Henríquez | D7: Coordinación del portafolio | E7: DTE Consulting & Development SpA | I7: =F7+G7+H7 -> 0
B8: 3 | C8: Mauricio Pruzzo Gárate | D8: Especialista normativo y territorial | E8: DTE Consulting & Development SpA | I8: =F8+G8+H8 -> 0
B9: 4 | C9: Nicolás Caro Zúñiga | D9: Coordinación de producto y difusión | E9: DTE Consulting & Development SpA | I9: =F9+G9+H9 -> 0
B10: 5 | C10: Ariel Ahoner Sáez Caamaño | D10: Líder técnico de inteligencia artificial | E10: Impulso Estratégico CX SpA | G10: =('Aporte Participantes Programa'!E$14/2+'Aporte Participantes Programa'!E$8)/3 -> 0 | H10: =('Aporte Participantes Programa'!F$8+'Aporte Participantes Programa'!F$14/2)/3 -> 37500000 | I10: =F10+G10+H10 -> 37500000
B11: 6 | C11: Federico Orduz | D11: Equipo técnico de desarrollo de IA y know-how aplicado al producto conjunto (P1) | E11: Impulso Estratégico CX SpA | G11: =('Aporte Participantes Programa'!E$14/2+'Aporte Participantes Programa'!E$8)/3 -> 0 | H11: =('Aporte Participantes Programa'!F$8+'Aporte Participantes Programa'!F$14/2)/3 -> 37500000 | I11: =F11+G11+H11 -> 37500000
B12: 7 | C12: Mauricio Chamorro | D12: Equipo técnico de desarrollo de IA y know-how aplicado al producto conjunto (P1) | E12: Impulso Estratégico CX SpA | G12: =('Aporte Participantes Programa'!E$14/2+'Aporte Participantes Programa'!E$8)/3 -> 0 | H12: =('Aporte Participantes Programa'!F$8+'Aporte Participantes Programa'!F$14/2)/3 -> 37500000 | I12: =F12+G12+H12 -> 37500000
B13: 8 | C13: Cristobal Campora | D13: Equipo de programación y análisis de big data inmobiliario (P1) | E13: In-Data | G13: =('Aporte Participantes Programa'!E$13/2+'Aporte Participantes Programa'!E$10)/2 -> 20000000 | H13: =('Aporte Participantes Programa'!F$14/2+'Aporte Participantes Programa'!F$9)/2 -> 56750000 | I13: =F13+G13+H13 -> 76750000
B14: 9 | C14: Daniel Minaya | D14: Equipo de programación y análisis de big data inmobiliario (P1) | E14: In-Data | G14: =('Aporte Participantes Programa'!E$13/2+'Aporte Participantes Programa'!E$10)/2 -> 20000000 | H14: =('Aporte Participantes Programa'!F$14/2+'Aporte Participantes Programa'!F$9)/2 -> 56750000 | I14: =F14+G14+H14 -> 76750000
B15: 10 | C15: Nicolás Geister | D15: Equipo BIM y coordinación de especialidades | E15: Geister | G15: =('Aporte Participantes Programa'!E$10+'Aporte Participantes Programa'!E$13)/2 -> 20000000 | H15: =('Aporte Participantes Programa'!F$10+'Aporte Participantes Programa'!F$13)/2 -> 64500000 | I15: =F15+G15+H15 -> 84500000
B16: 11 | C16: Antonia Jimenez | D16: Equipo BIM y coordinación de especialidades | E16: Geister | G16: =('Aporte Participantes Programa'!E$10+'Aporte Participantes Programa'!E$13)/2 -> 20000000 | H16: =('Aporte Participantes Programa'!F$10+'Aporte Participantes Programa'!F$13)/2 -> 64500000 | I16: =F16+G16+H16 -> 84500000
B17: 12 | C17: Carlos Herrera | D17: Equipo de precios, presupuestos y programa de compras (P2, P3 y P4) | E17: ONDAC | G17: ='Aporte Participantes Programa'!E$11/2 -> 20000000 | H17: ='Aporte Participantes Programa'!F$11/2 -> 50000000 | I17: =F17+G17+H17 -> 70000000
B18: 13 | C18: Carlos Zambrano | D18: Equipo de precios, presupuestos y programa de compras (P2, P3 y P4) | E18: ONDAC | G18: ='Aporte Participantes Programa'!E$11/2 -> 20000000 | H18: ='Aporte Participantes Programa'!F$11/2 -> 50000000 | I18: =F18+G18+H18 -> 70000000
B19: 14 | C19: Ricardo León | D19: Equipo de facility management y normalización de protocolos (P3 y P4) | E19: Calidad Cloud | G19: ='Aporte Participantes Programa'!E$12/2 -> 20000000 | H19: ='Aporte Participantes Programa'!F$12/2 -> 50000000 | I19: =F19+G19+H19 -> 70000000
B20: 15 | C20: Franze Fahrenkrog | D20: Equipo de facility management y normalización de protocolos (P3 y P4) | E20: Calidad Cloud | G20: ='Aporte Participantes Programa'!E$12/2 -> 20000000 | H20: ='Aporte Participantes Programa'!F$12/2 -> 50000000 | I20: =F20+G20+H20 -> 70000000
I21: =F21+G21+H21 -> 0
I22: =F22+G22+H22 -> 0
I23: =F23+G23+H23 -> 0
B24: TOTAL | F24: =SUM(F6:F23) -> 0 | G24: =SUM(G6:G23) -> 160000000 | H24: =SUM(H6:H23) -> 555000000 | I24: =F24+G24+H24 -> 715000000
F25: 600000000 | G25: ='Aporte Participantes Programa'!E16 -> 760000000 | H25: ='Aporte Participantes Programa'!F16 -> 655000000
B28: Refiérase a la descripción establecida en las bases técnicas, en el subnumeral 7.1 Actividades y gastos generales del proyecto a) equipo de trabajo del programa
B29: a) Equipo de trabajo del Programa, cuya participación sea necesaria y esté directamente vinculada a la ejecución del mismo, el cual deberá presupuestarse en la cuenta “Recursos Humanos”.
C30: - Con recursos del subsidio, se podrá financiar las remuneraciones y/u honorarios del personal nuevo y/o preexistente del beneficiario y/o coejecutor(es). No se establecen topes de subsidio para financiar al personal nuevo, no obstante, sólo se podrá destinar como máximo hasta un 25.00% del mismo al personal preexistente. Se entiende por personal preexistente el que esté contratado por el participante al momento de la postulación.
C31: - Con aportes del beneficiario, coejecutor y/o asociados, se podrán financiar las remuneraciones y/u honorarios de personal nuevo y/o prexistente de los mismos (este último caso aplica sólo cuando en el llamado se permitan aportes “preexistentes” o “valorados”).

Sheet Detalle Inversiones
B1: PROGRAMA TECNOLÓGICO BITÁCORA: LÍNEA DE VIDA DE UN ACTIVO INMOBILIARIO
B3: PROGRAMAS TECNOLÓGICOS - DESCRIPCIÓN INVERSIONES POR PROYECTO (Considere la descripción establecida en el numeral 11 de las Bases Técnicas y subnumeral 4.6 de las Bases Administrativas Generales)
B5: N° | C5: NOMBRE PROYECTO | D5: NOMBRE INVERSIÓN | E5: JUSTIFICACIÓN | F5: SUBSIDIO CORFO ($) | G5: APORTE PROGRAMA TECNOLÓGICO ($) | H5: TOTAL PROGRAMA ($) | I5: MES DE COMPRA
B6: 1 | C6: P1 · Evaluación del activo y búsqueda de terreno con IA (piloto DS49) | D6: Computadores y servidores con capacidades de trabajar con IA | E6: Procesamiento de datos territoriales y entrenamiento de los modelos del índice de terreno | F6: ='Presupuesto Total'!F8 -> 15000000 | H6: =F6+G6 -> 15000000 | I6: 5
B7: 2 | C7: P2 · Desarrollo y optimización del proyecto (CAPEX, OPEX y plazos) | D7: Equipamiento y licencias capitalizables de modelación BIM | E7: Modelación de alternativas de proyecto y cálculo de costos de ciclo de vida | F7: ='Presupuesto Total'!F9 -> 15000000 | H7: =F7+G7 -> 15000000 | I7: 5
B8: 3 | C8: P3 · Integración de especialistas en obra ("Zapatilla") | D8: Equipamiento de captura en obra (tabletas robustas y sensores) | E8: Registro en terreno de avance, calidad y seguridad para los cuatro índices de obra | F8: ='Presupuesto Total'!F10 -> 15000000 | H8: =F8+G8 -> 15000000 | I8: 5
B9: 4 | C9: P4 · Mantenimiento predictivo y línea de vida del activo | D9: Infraestructura de datos para operación y mantenimiento | E9: Histórico del activo, garantías y predicción de mantenciones durante la operación | F9: ='Presupuesto Total'!F11 -> 15000000 | H9: =F9+G9 -> 15000000 | I9: 5
B28: TOTAL | F28: =SUM(F6:F27) -> 60000000 | G28: =SUM(G6:G27) -> 0 | H28: =SUM(H6:H27) -> 60000000

Sheet Presupuesto por Fuente
B1: PROGRAMA TECNOLÓGICO BITÁCORA: LÍNEA DE VIDA DE UN ACTIVO INMOBILIARIO
B3: PROGRAMAS TECNOLÓGICOS - PRESUPUESTO TOTAL POR FUENTE DE FINANCIAMIENTO
E4: APORTES PARTICIPANTES DEL PROGRAMA | V4: COSTO TOTAL PROGRAMA ($)
B5: N° DE PROYECTO | C5: NOMBRE CORTO DEL PROYECTO | D5: SUBSIDIO TOTAL CORFO | E5: BENEFICIARIA | G5: COEJECUTOR 1 | I5: COEJECUTOR 2 | K5: COEJECUTOR 3 | M5: COEJECUTOR 4 | O5: COEJECUTOR 5 | Q5: ASOCIADO 1 | S5: ASOCIADO 2 | U5: APORTE TOTAL ($)
E6: APORTE PECUNIARIO ($) | F6: APORTE NO PECUNIARIO ($) | G6: APORTE PECUNIARIO ($) | H6: APORTE NO PECUNIARIO ($) | I6: APORTE PECUNIARIO ($) | J6: APORTE NO PECUNIARIO ($) | K6: APORTE PECUNIARIO ($) | L6: APORTE NO PECUNIARIO ($) | M6: APORTE PECUNIARIO ($) | N6: APORTE NO PECUNIARIO ($) | O6: APORTE PECUNIARIO ($) | P6: APORTE NO PECUNIARIO ($) | Q6: APORTE PECUNIARIO ($) | R6: APORTE NO PECUNIARIO ($) | S6: APORTE PECUNIARIO ($) | T6: APORTE NO PECUNIARIO ($)
B7: P0 | C7: Gestión y administración del Programa (OBLIGATORIO) | D7: ='Presupuesto Total'!H7 -> 897000000 | E7: 405000000 | F7: 30000000 | U7: =SUM(E7:T7) -> 435000000 | V7: =+D7+U7 -> 1332000000
B8: P1 | C8: Evaluación del activo y búsqueda de terreno con IA (piloto DS49) | D8: ='Presupuesto Total'!H8 -> 530000000 | E8: 110000000 | F8: 30000000 | H8: 150000000 | I8: ='Aporte Participantes Programa'!E9+'Aporte Participantes Programa'!G9 -> 50000000 | J8: ='Aporte Participantes Programa'!F9+'Aporte Participantes Programa'!H9 -> 150000000 | R8: 25000000 | U8: =SUM(E8:T8) -> 515000000 | V8: =+D8+U8 -> 1045000000
B9: P2 | C9: Desarrollo y optimización del proyecto (CAPEX, OPEX y plazos) | D9: ='Presupuesto Total'!H9 -> 530000000 | E9: 110000000 | F9: 30000000 | K9: ='Aporte Participantes Programa'!E10+'Aporte Participantes Programa'!G10 -> 50000000 | L9: ='Aporte Participantes Programa'!F10+'Aporte Participantes Programa'!H10 -> 150000000 | T9: 30000000 | U9: =SUM(E9:T9) -> 370000000 | V9: =+D9+U9 -> 900000000
B10: P3 | C10: Integración de especialistas en obra ("Zapatilla") | D10: ='Presupuesto Total'!H10 -> 528000000 | E10: 110000000 | F10: 30000000 | M10: ='Aporte Participantes Programa'!E11+'Aporte Participantes Programa'!G11 -> 50000000 | N10: ='Aporte Participantes Programa'!F11+'Aporte Participantes Programa'!H11 -> 150000000 | U10: =SUM(E10:T10) -> 340000000 | V10: =+D10+U10 -> 868000000
B11: P4 | C11: Mantenimiento predictivo y línea de vida del activo | D11: ='Presupuesto Total'!H11 -> 515000000 | E11: 110000000 | F11: 30000000 | O11: ='Aporte Participantes Programa'!E12+'Aporte Participantes Programa'!G12 -> 50000000 | P11: ='Aporte Participantes Programa'!F12+'Aporte Participantes Programa'!H12 -> 150000000 | U11: =SUM(E11:T11) -> 340000000 | V11: =+D11+U11 -> 855000000
U12: =SUM(E12:T12) -> 0 | V12: =+D12+U12 -> 0
U13: =SUM(E13:T13) -> 0 | V13: =+D13+U13 -> 0
U14: =SUM(E14:T14) -> 0 | V14: =+D14+U14 -> 0
U15: =SUM(E15:T15) -> 0 | V15: =+D15+U15 -> 0
U16: =SUM(E16:T16) -> 0 | V16: =+D16+U16 -> 0
U17: =SUM(E17:T17) -> 0 | V17: =+D17+U17 -> 0
C18: TOTAL PROGRAMA | D18: =SUM(D7:D17) -> 3000000000 | E18: =SUM(E7:E17) -> 845000000 | F18: =SUM(F7:F17) -> 150000000 | G18: =SUM(G7:G17) -> 0 | H18: =SUM(H7:H17) -> 150000000 | I18: =SUM(I7:I17) -> 50000000 | J18: =SUM(J7:J17) -> 150000000 | K18: =SUM(K7:K17) -> 50000000 | ... V18: =SUM(V7:V17) -> 5000000000

Sheet Carta Gantt
B1: PROGRAMA TECNOLÓGICO BITÁCORA: LÍNEA DE VIDA DE UN ACTIVO INMOBILIARIO
B3: PROGRAMAS TECNOLÓGICOS - CARTA GANTT (Debe incluir Proyecto de Gestión y Administración)
B5: N° Proyecto | C5: Nombre del proyecto | D5: AÑO 1 | P5: AÑO 2 | AB5: AÑO 3 | AN5: AÑO 4 | AZ5: AÑO 5
D6: 1 | E6: 2 | F6: 3 | G6: 4 | H6: 5 | I6: 6 | J6: 7 | K6: 8 | L6: 9 | M6: 10 | N6: 11 | O6: 12 | P6: 13 | Q6: 14 | R6: 15 | S6: 16 | T6: 17 | U6: 18 | V6: 19 | W6: 20 | X6: 21 | Y6: 22 | Z6: 23 | AA6: 24 | AB6: 25 | AC6: 26 | AD6: 27 | AE6: 28 | AF6: 29 | AG6: 30 | AH6: 31 | AI6: 32 | AJ6: 33 | AK6: 34 | AL6: 35 | AM6: 36 | AN6: 37 | AO6: 38 | AP6: 39 | AQ6: 40 | AR6: 41 | AS6: 42 | AT6: 43 | AU6: 44 | AV6: 45 | AW6: 46 | AX6: 47 | AY6: 48 | AZ6: 49 | BA6: 50 | BB6: 51 | BC6: 52 | BD6: 53 | BE6: 54 | BF6: 55 | BG6: 56 | BH6: 57 | BI6: 58 | BJ6: 59 | BK6: 60
B7: P0 | C7: Gestión y administración del Programa (OBLIGATORIO)
B8: P1 | C8: Evaluación del activo y búsqueda de terreno con IA (piloto DS49)
B9: P2 | C9: Desarrollo y optimización del proyecto (CAPEX, OPEX y plazos)
B10: P3 | C10: Integración de especialistas en obra ("Zapatilla")
B11: P4 | C11: Mantenimiento predictivo y línea de vida del activo

Sheet Detalle Presupuesto por Cuenta
B1: PROGRAMA TECNOLÓGICO BITÁCORA: LÍNEA DE VIDA DE UN ACTIVO INMOBILIARIO
B3: PROGRAMAS TECNOLÓGICOS - DETALLE PRESUPUESTO POR CUENTAS
C4: N° | D4: SUBSIDIO CORFO $ | E4: APORTE PROGRAMA TECNOLÓGICO | G4: TOTAL PROGRAMA (S)
E5: Pecuniario $ | F5: Valorizado $
B6: RECURSOS HUMANOS ($) (Sólo se podrá destinar como máximo hasta un 25,00% del subsidio a personal preexistente, de acuerdo al Subnumeral 7.1 de las bases técnica)
B7: Profesionales (Nuevos y Preexistentes) | C7: 37 | D7: 1772800000 | E7: 450000000 | F7: 600000000 | G7: =+SUM(D7:F7) -> 2822800000
B8: Técnicos (Nuevos y Preexistentes) | C8: 11 | D8: 127200000 | E8: 120000000 | F8: 150000000 | G8: =+SUM(D8:F8) -> 397200000
B9: Otros (Nuevos y Preexistentes) | C9: 3 | E9: 30000000 | G9: =+SUM(D9:F9) -> 30000000
B10: TOTAL | D10: =SUM(D7:D9) -> 1900000000 | E10: =SUM(E7:E9) -> 600000000 | F10: =SUM(F7:F9) -> 750000000 | G10: =SUM(G7:G9) -> 3250000000
B11: GASTOS DE OPERACIÓN ($)
B12: Estudios o similares | D12: 130000000 | G12: =+SUM(D12:F12) -> 130000000
B13: Insumos varios | D13: 290000000 | E13: 180000000 | G13: =+SUM(D13:F13) -> 470000000
B14: Analisis de laboratorio | G14: =+SUM(D14:F14) -> 0
B15: Adecuación/Mantención Infraestructura (no inversión) | G15: =+SUM(D15:F15) -> 0
B16: Viáticos, Movilización, traslado matriales y logística | D16: 120000000 | E16: 120000000 | G16: =+SUM(D16:F16) -> 240000000
B17: Comunicación y difusión | D17: 40000000 | G17: =+SUM(D17:F17) -> 40000000
B18: Uso de equipamiento e infraestrutura para desarrollo del proyecto) | F18: 250000000 | G18: =+SUM(D18:F18) -> 250000000
B19: Materias primas para pruebas pilotos | G19: =+SUM(D19:F19) -> 0
B20: Asesoria legal, contratos protección de Pi, actividades afines | D20: 20000000 | G20: =+SUM(D20:F20) -> 20000000
B21: Estudios de impacto ambiental | G21: =+SUM(D21:F21) -> 0
B22: Certificaciones y regulaciones | D22: 50000000 | G22: =+SUM(D22:F22) -> 50000000
B23: Otros | G23: =+SUM(D23:F23) -> 0
B24: TOTAL | D24: =SUM(D12:D23) -> 650000000 | E24: =SUM(E12:E23) -> 300000000 | F24: =SUM(F12:F23) -> 250000000 | G24: =SUM(G12:G23) -> 1200000000
B25: INVERSIÓN ($) (No puede superar el 30,00% del subsidio solicitado, de acuerdo al numeral 11 de las Bases del Instrumento. Aspectos Presupuestarios de las Bases Técnicas)
B26: Equipamiento | D26: 200000000 | E26: 60000000 | G26: =+SUM(D26:F26) -> 260000000
B27: Infraestructura | G27: =+SUM(D27:F27) -> 0
B28: Otros | D28: 50000000 | G28: =+SUM(D28:F28) -> 50000000
B29: TOTAL | D29: =SUM(D26:D28) -> 250000000 | E29: =SUM(E26:E28) -> 60000000 | F29: =SUM(F26:F28) -> 0 | G29: =SUM(G26:G28) -> 310000000
B30: ADMINISTRACIÓN ($) (Se podrá destinar como máximo hasta un 10% del subsidio a este tipo de gastos, de acuerdo al numeral 11 de las Bases del Instrumento. Aspectos Presupuestarios de las Bases Técnicas)
B31: Servicios básicos | D31: 40000000 | G31: =+SUM(D31:F31) -> 40000000
B32: Servicios de Contabilidad | D32: 60000000 | G32: =+SUM(D32:F32) -> 60000000
B33: Personal Administrativo de apoyo | D33: 100000000 | E33: 40000000 | G33: =+SUM(D33:F33) -> 140000000
B34: Otros | G34: =+SUM(D34:F34) -> 0
B35: TOTAL | D35: =SUM(D31:D34) -> 200000000 | E35: =SUM(E31:E34) -> 40000000 | F35: =SUM(F31:F34) -> 0 | G35: =SUM(G31:G34) -> 240000000
